<additional>
    <flow id="1070403831#1-AddedOnRampEdge_1040737038.qPKW.0" departSpeed="max" departPos="last" departLane="best" route="1070403831#1-AddedOnRampEdge_1040737038.qPKW.0" number="4" begin="0" end="30.0"/>
    <flow id="19441652#0_19442635.qPKW.0" departSpeed="max" departPos="last" departLane="best" route="19441652#0_19442635.qPKW.0" number="2" begin="0" end="30.0"/>
    <flow id="277208926_634155175.qPKW.0" departSpeed="max" departPos="last" departLane="best" route="277208926_634155175.qPKW.0" number="2" begin="0" end="30.0"/>
    <flow id="27828382_634155175.qPKW.0" departSpeed="max" departPos="last" departLane="best" route="27828382_634155175.qPKW.0" number="1" begin="0" end="30.0"/>
    <flow id="19441652#0_19442635.qPKW.0.5" departSpeed="max" departPos="last" departLane="best" route="19441652#0_19442635.qPKW.0.5" number="6" begin="30.0" end="60.0"/>
    <flow id="27828382_634155175.qPKW.0.5" departSpeed="max" departPos="last" departLane="best" route="27828382_634155175.qPKW.0.5" number="4" begin="30.0" end="60.0"/>
    <flow id="277208926_634155175.qPKW.1.0" departSpeed="max" departPos="last" departLane="best" route="277208926_634155175.qPKW.1.0" number="8" begin="60.0" end="90.0"/>
    <flow id="27828382_1040737038.qPKW.1.0" departSpeed="max" departPos="last" departLane="best" route="27828382_1040737038.qPKW.1.0" number="14" begin="60.0" end="90.0"/>
    <flow id="27828382_634155175.qPKW.1.0" departSpeed="max" departPos="last" departLane="best" route="27828382_634155175.qPKW.1.0" number="2" begin="60.0" end="90.0"/>
    <flow id="277208926_634155175.qPKW.1.5" departSpeed="max" departPos="last" departLane="best" route="277208926_634155175.qPKW.1.5" number="2" begin="90.0" end="120.0"/>
    <flow id="27828382_1040737038.qPKW.1.5" departSpeed="max" departPos="last" departLane="best" route="27828382_1040737038.qPKW.1.5" number="1" begin="90.0" end="120.0"/>
    <flow id="27828382_634155175.qPKW.1.5" departSpeed="max" departPos="last" departLane="best" route="27828382_634155175.qPKW.1.5" number="4" begin="90.0" end="120.0"/>
    <flow id="19441652#0_19442635.qPKW.2.0" departSpeed="max" departPos="last" departLane="best" route="19441652#0_19442635.qPKW.2.0" number="2" begin="120.0" end="150.0"/>
    <flow id="27828382_1040737038.qPKW.2.0" departSpeed="max" departPos="last" departLane="best" route="27828382_1040737038.qPKW.2.0" number="7" begin="120.0" end="150.0"/>
    <flow id="27828382_634155175.qPKW.2.0" departSpeed="max" departPos="last" departLane="best" route="27828382_634155175.qPKW.2.0" number="5" begin="120.0" end="150.0"/>
    <flow id="1070403831#1-AddedOnRampEdge_1040737038.qPKW.2.5" departSpeed="max" departPos="last" departLane="best" route="1070403831#1-AddedOnRampEdge_1040737038.qPKW.2.5" number="8" begin="150.0" end="180.0"/>
    <flow id="1070403831#1-AddedOnRampEdge_19442635.qPKW.2.5" departSpeed="max" departPos="last" departLane="best" route="1070403831#1-AddedOnRampEdge_19442635.qPKW.2.5" number="1" begin="150.0" end="180.0"/>
    <flow id="19441652#0_19442635.qPKW.2.5" departSpeed="max" departPos="last" departLane="best" route="19441652#0_19442635.qPKW.2.5" number="1" begin="150.0" end="180.0"/>
    <flow id="27828382_1040737038.qPKW.2.5" departSpeed="max" departPos="last" departLane="best" route="27828382_1040737038.qPKW.2.5" number="9" begin="150.0" end="180.0"/>
    <flow id="27828382_634155175.qPKW.2.5" departSpeed="max" departPos="last" departLane="best" route="27828382_634155175.qPKW.2.5" number="8" begin="150.0" end="180.0"/>
    <flow id="1070403831#1-AddedOnRampEdge_1040737038.qPKW.3.0" departSpeed="max" departPos="last" departLane="best" route="1070403831#1-AddedOnRampEdge_1040737038.qPKW.3.0" number="6" begin="180.0" end="210.0"/>
    <flow id="1070403831#1-AddedOnRampEdge_19442635.qPKW.3.0" departSpeed="max" departPos="last" departLane="best" route="1070403831#1-AddedOnRampEdge_19442635.qPKW.3.0" number="10" begin="180.0" end="210.0"/>
    <flow id="27828382_1040737038.qPKW.3.0" departSpeed="max" departPos="last" departLane="best" route="27828382_1040737038.qPKW.3.0" number="4" begin="180.0" end="210.0"/>
    <flow id="27828382_634155175.qPKW.3.0" departSpeed="max" departPos="last" departLane="best" route="27828382_634155175.qPKW.3.0" number="10" begin="180.0" end="210.0"/>
    <flow id="1070403831#1-AddedOnRampEdge_1040737038.qPKW.3.5" departSpeed="max" departPos="last" departLane="best" route="1070403831#1-AddedOnRampEdge_1040737038.qPKW.3.5" number="1" begin="210.0" end="240.0"/>
    <flow id="1070403831#1-AddedOnRampEdge_19442635.qPKW.3.5" departSpeed="max" departPos="last" departLane="best" route="1070403831#1-AddedOnRampEdge_19442635.qPKW.3.5" number="10" begin="210.0" end="240.0"/>
    <flow id="19441652#0_19442635.qPKW.3.5" departSpeed="max" departPos="last" departLane="best" route="19441652#0_19442635.qPKW.3.5" number="1" begin="210.0" end="240.0"/>
    <flow id="27828382_1040737038.qPKW.3.5" departSpeed="max" departPos="last" departLane="best" route="27828382_1040737038.qPKW.3.5" number="6" begin="210.0" end="240.0"/>
    <flow id="27828382_634155175.qPKW.3.5" departSpeed="max" departPos="last" departLane="best" route="27828382_634155175.qPKW.3.5" number="13" begin="210.0" end="240.0"/>
    <flow id="1070403831#1-AddedOnRampEdge_1040737038.qPKW.4.0" departSpeed="max" departPos="last" departLane="best" route="1070403831#1-AddedOnRampEdge_1040737038.qPKW.4.0" number="1" begin="240.0" end="270.0"/>
    <flow id="1070403831#1-AddedOnRampEdge_19442635.qPKW.4.0" departSpeed="max" departPos="last" departLane="best" route="1070403831#1-AddedOnRampEdge_19442635.qPKW.4.0" number="13" begin="240.0" end="270.0"/>
    <flow id="19441652#0_19442635.qPKW.4.0" departSpeed="max" departPos="last" departLane="best" route="19441652#0_19442635.qPKW.4.0" number="1" begin="240.0" end="270.0"/>
    <flow id="27828382_1040737038.qPKW.4.0" departSpeed="max" departPos="last" departLane="best" route="27828382_1040737038.qPKW.4.0" number="2" begin="240.0" end="270.0"/>
    <flow id="27828382_634155175.qPKW.4.0" departSpeed="max" departPos="last" departLane="best" route="27828382_634155175.qPKW.4.0" number="15" begin="240.0" end="270.0"/>
    <flow id="1070403831#1-AddedOnRampEdge_1040737038.qPKW.4.5" departSpeed="max" departPos="last" departLane="best" route="1070403831#1-AddedOnRampEdge_1040737038.qPKW.4.5" number="9" begin="270.0" end="300.0"/>
    <flow id="1070403831#1-AddedOnRampEdge_19442635.qPKW.4.5" departSpeed="max" departPos="last" departLane="best" route="1070403831#1-AddedOnRampEdge_19442635.qPKW.4.5" number="6" begin="270.0" end="300.0"/>
    <flow id="19441652#0_19442635.qPKW.4.5" departSpeed="max" departPos="last" departLane="best" route="19441652#0_19442635.qPKW.4.5" number="5" begin="270.0" end="300.0"/>
    <flow id="277208926_634155175.qPKW.4.5" departSpeed="max" departPos="last" departLane="best" route="277208926_634155175.qPKW.4.5" number="9" begin="270.0" end="300.0"/>
    <flow id="27828382_634155175.qPKW.4.5" departSpeed="max" departPos="last" departLane="best" route="27828382_634155175.qPKW.4.5" number="17" begin="270.0" end="300.0"/>
    <flow id="1070403831#1-AddedOnRampEdge_1040737038.qPKW.5.0" departSpeed="max" departPos="last" departLane="best" route="1070403831#1-AddedOnRampEdge_1040737038.qPKW.5.0" number="5" begin="300.0" end="330.0"/>
    <flow id="1070403831#1-AddedOnRampEdge_19442635.qPKW.5.0" departSpeed="max" departPos="last" departLane="best" route="1070403831#1-AddedOnRampEdge_19442635.qPKW.5.0" number="11" begin="300.0" end="330.0"/>
    <flow id="19441652#0_19442635.qPKW.5.0" departSpeed="max" departPos="last" departLane="best" route="19441652#0_19442635.qPKW.5.0" number="2" begin="300.0" end="330.0"/>
    <flow id="277208926_634155175.qPKW.5.0" departSpeed="max" departPos="last" departLane="best" route="277208926_634155175.qPKW.5.0" number="11" begin="300.0" end="330.0"/>
    <flow id="27828382_634155175.qPKW.5.0" departSpeed="max" departPos="last" departLane="best" route="27828382_634155175.qPKW.5.0" number="16" begin="300.0" end="330.0"/>
    <flow id="1070403831#1-AddedOnRampEdge_1040737038.qPKW.5.5" departSpeed="max" departPos="last" departLane="best" route="1070403831#1-AddedOnRampEdge_1040737038.qPKW.5.5" number="5" begin="330.0" end="360.0"/>
    <flow id="1070403831#1-AddedOnRampEdge_19442635.qPKW.5.5" departSpeed="max" departPos="last" departLane="best" route="1070403831#1-AddedOnRampEdge_19442635.qPKW.5.5" number="8" begin="330.0" end="360.0"/>
    <flow id="19441652#0_19442635.qPKW.5.5" departSpeed="max" departPos="last" departLane="best" route="19441652#0_19442635.qPKW.5.5" number="8" begin="330.0" end="360.0"/>
    <flow id="277208926_634155175.qPKW.5.5" departSpeed="max" departPos="last" departLane="best" route="277208926_634155175.qPKW.5.5" number="11" begin="330.0" end="360.0"/>
    <flow id="27828382_634155175.qPKW.5.5" departSpeed="max" departPos="last" departLane="best" route="27828382_634155175.qPKW.5.5" number="15" begin="330.0" end="360.0"/>
    <flow id="1070403831#1-AddedOnRampEdge_1040737038.qPKW.6.0" departSpeed="max" departPos="last" departLane="best" route="1070403831#1-AddedOnRampEdge_1040737038.qPKW.6.0" number="11" begin="360.0" end="390.0"/>
    <flow id="1070403831#1-AddedOnRampEdge_19442635.qPKW.6.0" departSpeed="max" departPos="last" departLane="best" route="1070403831#1-AddedOnRampEdge_19442635.qPKW.6.0" number="3" begin="360.0" end="390.0"/>
    <flow id="19441652#0_19442635.qPKW.6.0" departSpeed="max" departPos="last" departLane="best" route="19441652#0_19442635.qPKW.6.0" number="9" begin="360.0" end="390.0"/>
    <flow id="277208926_634155175.qPKW.6.0" departSpeed="max" departPos="last" departLane="best" route="277208926_634155175.qPKW.6.0" number="8" begin="360.0" end="390.0"/>
    <flow id="27828382_634155175.qPKW.6.0" departSpeed="max" departPos="last" departLane="best" route="27828382_634155175.qPKW.6.0" number="18" begin="360.0" end="390.0"/>
    <flow id="1070403831#1-AddedOnRampEdge_1040737038.qPKW.6.5" departSpeed="max" departPos="last" departLane="best" route="1070403831#1-AddedOnRampEdge_1040737038.qPKW.6.5" number="4" begin="390.0" end="420.0"/>
    <flow id="1070403831#1-AddedOnRampEdge_19442635.qPKW.6.5" departSpeed="max" departPos="last" departLane="best" route="1070403831#1-AddedOnRampEdge_19442635.qPKW.6.5" number="13" begin="390.0" end="420.0"/>
    <flow id="277208926_634155175.qPKW.6.5" departSpeed="max" departPos="last" departLane="best" route="277208926_634155175.qPKW.6.5" number="14" begin="390.0" end="420.0"/>
    <flow id="27828382_634155175.qPKW.6.5" departSpeed="max" departPos="last" departLane="best" route="27828382_634155175.qPKW.6.5" number="15" begin="390.0" end="420.0"/>
    <flow id="1070403831#1-AddedOnRampEdge_1040737038.qPKW.7.0" departSpeed="max" departPos="last" departLane="best" route="1070403831#1-AddedOnRampEdge_1040737038.qPKW.7.0" number="6" begin="420.0" end="450.0"/>
    <flow id="1070403831#1-AddedOnRampEdge_19442635.qPKW.7.0" departSpeed="max" departPos="last" departLane="best" route="1070403831#1-AddedOnRampEdge_19442635.qPKW.7.0" number="7" begin="420.0" end="450.0"/>
    <flow id="19441652#0_19442635.qPKW.7.0" departSpeed="max" departPos="last" departLane="best" route="19441652#0_19442635.qPKW.7.0" number="7" begin="420.0" end="450.0"/>
    <flow id="277208926_634155175.qPKW.7.0" departSpeed="max" departPos="last" departLane="best" route="277208926_634155175.qPKW.7.0" number="11" begin="420.0" end="450.0"/>
    <flow id="27828382_634155175.qPKW.7.0" departSpeed="max" departPos="last" departLane="best" route="27828382_634155175.qPKW.7.0" number="18" begin="420.0" end="450.0"/>
    <flow id="1070403831#1-AddedOnRampEdge_1040737038.qPKW.7.5" departSpeed="max" departPos="last" departLane="best" route="1070403831#1-AddedOnRampEdge_1040737038.qPKW.7.5" number="6" begin="450.0" end="480.0"/>
    <flow id="1070403831#1-AddedOnRampEdge_19442635.qPKW.7.5" departSpeed="max" departPos="last" departLane="best" route="1070403831#1-AddedOnRampEdge_19442635.qPKW.7.5" number="8" begin="450.0" end="480.0"/>
    <flow id="19441652#0_19442635.qPKW.7.5" departSpeed="max" departPos="last" departLane="best" route="19441652#0_19442635.qPKW.7.5" number="5" begin="450.0" end="480.0"/>
    <flow id="277208926_634155175.qPKW.7.5" departSpeed="max" departPos="last" departLane="best" route="277208926_634155175.qPKW.7.5" number="12" begin="450.0" end="480.0"/>
    <flow id="27828382_634155175.qPKW.7.5" departSpeed="max" departPos="last" departLane="best" route="27828382_634155175.qPKW.7.5" number="16" begin="450.0" end="480.0"/>
    <flow id="1070403831#1-AddedOnRampEdge_1040737038.qPKW.8.0" departSpeed="max" departPos="last" departLane="best" route="1070403831#1-AddedOnRampEdge_1040737038.qPKW.8.0" number="7" begin="480.0" end="510.0"/>
    <flow id="1070403831#1-AddedOnRampEdge_19442635.qPKW.8.0" departSpeed="max" departPos="last" departLane="best" route="1070403831#1-AddedOnRampEdge_19442635.qPKW.8.0" number="7" begin="480.0" end="510.0"/>
    <flow id="19441652#0_19442635.qPKW.8.0" departSpeed="max" departPos="last" departLane="best" route="19441652#0_19442635.qPKW.8.0" number="5" begin="480.0" end="510.0"/>
    <flow id="277208926_634155175.qPKW.8.0" departSpeed="max" departPos="last" departLane="best" route="277208926_634155175.qPKW.8.0" number="11" begin="480.0" end="510.0"/>
    <flow id="27828382_634155175.qPKW.8.0" departSpeed="max" departPos="last" departLane="best" route="27828382_634155175.qPKW.8.0" number="17" begin="480.0" end="510.0"/>
    <flow id="1070403831#1-AddedOnRampEdge_1040737038.qPKW.8.5" departSpeed="max" departPos="last" departLane="best" route="1070403831#1-AddedOnRampEdge_1040737038.qPKW.8.5" number="17" begin="510.0" end="540.0"/>
    <flow id="19441652#0_19442635.qPKW.8.5" departSpeed="max" departPos="last" departLane="best" route="19441652#0_19442635.qPKW.8.5" number="7" begin="510.0" end="540.0"/>
    <flow id="277208926_634155175.qPKW.8.5" departSpeed="max" departPos="last" departLane="best" route="277208926_634155175.qPKW.8.5" number="9" begin="510.0" end="540.0"/>
    <flow id="27828382_1040737038.qPKW.8.5" departSpeed="max" departPos="last" departLane="best" route="27828382_1040737038.qPKW.8.5" number="3" begin="510.0" end="540.0"/>
    <flow id="27828382_634155175.qPKW.8.5" departSpeed="max" departPos="last" departLane="best" route="27828382_634155175.qPKW.8.5" number="15" begin="510.0" end="540.0"/>
    <flow id="1070403831#1-AddedOnRampEdge_1040737038.qPKW.9.0" departSpeed="max" departPos="last" departLane="best" route="1070403831#1-AddedOnRampEdge_1040737038.qPKW.9.0" number="2" begin="540.0" end="570.0"/>
    <flow id="1070403831#1-AddedOnRampEdge_19442635.qPKW.9.0" departSpeed="max" departPos="last" departLane="best" route="1070403831#1-AddedOnRampEdge_19442635.qPKW.9.0" number="13" begin="540.0" end="570.0"/>
    <flow id="19441652#0_19442635.qPKW.9.0" departSpeed="max" departPos="last" departLane="best" route="19441652#0_19442635.qPKW.9.0" number="1" begin="540.0" end="570.0"/>
    <flow id="277208926_634155175.qPKW.9.0" departSpeed="max" departPos="last" departLane="best" route="277208926_634155175.qPKW.9.0" number="4" begin="540.0" end="570.0"/>
    <flow id="27828382_634155175.qPKW.9.0" departSpeed="max" departPos="last" departLane="best" route="27828382_634155175.qPKW.9.0" number="16" begin="540.0" end="570.0"/>
    <flow id="1070403831#1-AddedOnRampEdge_1040737038.qPKW.9.5" departSpeed="max" departPos="last" departLane="best" route="1070403831#1-AddedOnRampEdge_1040737038.qPKW.9.5" number="12" begin="570.0" end="600.0"/>
    <flow id="1070403831#1-AddedOnRampEdge_19442635.qPKW.9.5" departSpeed="max" departPos="last" departLane="best" route="1070403831#1-AddedOnRampEdge_19442635.qPKW.9.5" number="4" begin="570.0" end="600.0"/>
    <flow id="19441652#0_19442635.qPKW.9.5" departSpeed="max" departPos="last" departLane="best" route="19441652#0_19442635.qPKW.9.5" number="5" begin="570.0" end="600.0"/>
    <flow id="277208926_634155175.qPKW.9.5" departSpeed="max" departPos="last" departLane="best" route="277208926_634155175.qPKW.9.5" number="6" begin="570.0" end="600.0"/>
    <flow id="27828382_634155175.qPKW.9.5" departSpeed="max" departPos="last" departLane="best" route="27828382_634155175.qPKW.9.5" number="15" begin="570.0" end="600.0"/>
    <flow id="1070403831#1-AddedOnRampEdge_1040737038.qPKW.10.0" departSpeed="max" departPos="last" departLane="best" route="1070403831#1-AddedOnRampEdge_1040737038.qPKW.10.0" number="8" begin="600.0" end="630.0"/>
    <flow id="19441652#0_19442635.qPKW.10.0" departSpeed="max" departPos="last" departLane="best" route="19441652#0_19442635.qPKW.10.0" number="7" begin="600.0" end="630.0"/>
    <flow id="277208926_634155175.qPKW.10.0" departSpeed="max" departPos="last" departLane="best" route="277208926_634155175.qPKW.10.0" number="2" begin="600.0" end="630.0"/>
    <flow id="27828382_1040737038.qPKW.10.0" departSpeed="max" departPos="last" departLane="best" route="27828382_1040737038.qPKW.10.0" number="3" begin="600.0" end="630.0"/>
    <flow id="27828382_634155175.qPKW.10.0" departSpeed="max" departPos="last" departLane="best" route="27828382_634155175.qPKW.10.0" number="15" begin="600.0" end="630.0"/>
    <flow id="1070403831#1-AddedOnRampEdge_1040737038.qPKW.10.5" departSpeed="max" departPos="last" departLane="best" route="1070403831#1-AddedOnRampEdge_1040737038.qPKW.10.5" number="14" begin="630.0" end="660.0"/>
    <flow id="1070403831#1-AddedOnRampEdge_19442635.qPKW.10.5" departSpeed="max" departPos="last" departLane="best" route="1070403831#1-AddedOnRampEdge_19442635.qPKW.10.5" number="3" begin="630.0" end="660.0"/>
    <flow id="19441652#0_19442635.qPKW.10.5" departSpeed="max" departPos="last" departLane="best" route="19441652#0_19442635.qPKW.10.5" number="1" begin="630.0" end="660.0"/>
    <flow id="27828382_1040737038.qPKW.10.5" departSpeed="max" departPos="last" departLane="best" route="27828382_1040737038.qPKW.10.5" number="2" begin="630.0" end="660.0"/>
    <flow id="27828382_634155175.qPKW.10.5" departSpeed="max" departPos="last" departLane="best" route="27828382_634155175.qPKW.10.5" number="15" begin="630.0" end="660.0"/>
    <flow id="1070403831#1-AddedOnRampEdge_19442635.qPKW.11.0" departSpeed="max" departPos="last" departLane="best" route="1070403831#1-AddedOnRampEdge_19442635.qPKW.11.0" number="5" begin="660.0" end="690.0"/>
    <flow id="19441652#0_19442635.qPKW.11.0" departSpeed="max" departPos="last" departLane="best" route="19441652#0_19442635.qPKW.11.0" number="7" begin="660.0" end="690.0"/>
    <flow id="27828382_1040737038.qPKW.11.0" departSpeed="max" departPos="last" departLane="best" route="27828382_1040737038.qPKW.11.0" number="1" begin="660.0" end="690.0"/>
    <flow id="27828382_19442635.qPKW.11.0" departSpeed="max" departPos="last" departLane="best" route="27828382_19442635.qPKW.11.0" number="4" begin="660.0" end="690.0"/>
    <flow id="27828382_634155175.qPKW.11.0" departSpeed="max" departPos="last" departLane="best" route="27828382_634155175.qPKW.11.0" number="11" begin="660.0" end="690.0"/>
    <flow id="1070403831#1-AddedOnRampEdge_1040737038.qPKW.11.5" departSpeed="max" departPos="last" departLane="best" route="1070403831#1-AddedOnRampEdge_1040737038.qPKW.11.5" number="2" begin="690.0" end="720.0"/>
    <flow id="1070403831#1-AddedOnRampEdge_19442635.qPKW.11.5" departSpeed="max" departPos="last" departLane="best" route="1070403831#1-AddedOnRampEdge_19442635.qPKW.11.5" number="4" begin="690.0" end="720.0"/>
    <flow id="19441652#0_19442635.qPKW.11.5" departSpeed="max" departPos="last" departLane="best" route="19441652#0_19442635.qPKW.11.5" number="8" begin="690.0" end="720.0"/>
    <flow id="27828382_1040737038.qPKW.11.5" departSpeed="max" departPos="last" departLane="best" route="27828382_1040737038.qPKW.11.5" number="9" begin="690.0" end="720.0"/>
    <flow id="27828382_634155175.qPKW.11.5" departSpeed="max" departPos="last" departLane="best" route="27828382_634155175.qPKW.11.5" number="7" begin="690.0" end="720.0"/>
    <flow id="19441652#0_19442635.qPKW.12.0" departSpeed="max" departPos="last" departLane="best" route="19441652#0_19442635.qPKW.12.0" number="8" begin="720.0" end="750.0"/>
    <flow id="27828382_19442635.qPKW.12.0" departSpeed="max" departPos="last" departLane="best" route="27828382_19442635.qPKW.12.0" number="2" begin="720.0" end="750.0"/>
    <flow id="27828382_634155175.qPKW.12.0" departSpeed="max" departPos="last" departLane="best" route="27828382_634155175.qPKW.12.0" number="7" begin="720.0" end="750.0"/>
    <flow id="27828382_1040737038.qPKW.12.5" departSpeed="max" departPos="last" departLane="best" route="27828382_1040737038.qPKW.12.5" number="6" begin="750.0" end="780.0"/>
    <flow id="27828382_19442635.qPKW.12.5" departSpeed="max" departPos="last" departLane="best" route="27828382_19442635.qPKW.12.5" number="5" begin="750.0" end="780.0"/>
    <flow id="27828382_634155175.qPKW.12.5" departSpeed="max" departPos="last" departLane="best" route="27828382_634155175.qPKW.12.5" number="4" begin="750.0" end="780.0"/>
    <flow id="277208926_634155175.qPKW.13.0" departSpeed="max" departPos="last" departLane="best" route="277208926_634155175.qPKW.13.0" number="2" begin="780.0" end="810.0"/>
    <flow id="27828382_1040737038.qPKW.13.0" departSpeed="max" departPos="last" departLane="best" route="27828382_1040737038.qPKW.13.0" number="6" begin="780.0" end="810.0"/>
    <flow id="27828382_634155175.qPKW.13.0" departSpeed="max" departPos="last" departLane="best" route="27828382_634155175.qPKW.13.0" number="3" begin="780.0" end="810.0"/>
    <flow id="277208926_634155175.qPKW.13.5" departSpeed="max" departPos="last" departLane="best" route="277208926_634155175.qPKW.13.5" number="4" begin="810.0" end="840.0"/>
    <flow id="27828382_1040737038.qPKW.13.5" departSpeed="max" departPos="last" departLane="best" route="27828382_1040737038.qPKW.13.5" number="11" begin="810.0" end="840.0"/>
    <flow id="27828382_634155175.qPKW.13.5" departSpeed="max" departPos="last" departLane="best" route="27828382_634155175.qPKW.13.5" number="1" begin="810.0" end="840.0"/>
    <flow id="1070403831#1-AddedOnRampEdge_1040737038.qPKW.14.0" departSpeed="max" departPos="last" departLane="best" route="1070403831#1-AddedOnRampEdge_1040737038.qPKW.14.0" number="4" begin="840.0" end="870.0"/>
    <flow id="1070403831#1-AddedOnRampEdge_19442635.qPKW.14.0" departSpeed="max" departPos="last" departLane="best" route="1070403831#1-AddedOnRampEdge_19442635.qPKW.14.0" number="13" begin="840.0" end="870.0"/>
    <flow id="27828382_1040737038.qPKW.14.0" departSpeed="max" departPos="last" departLane="best" route="27828382_1040737038.qPKW.14.0" number="10" begin="840.0" end="870.0"/>
    <flow id="27828382_634155175.qPKW.14.0" departSpeed="max" departPos="last" departLane="best" route="27828382_634155175.qPKW.14.0" number="6" begin="840.0" end="870.0"/>
    <flow id="1070403831#1-AddedOnRampEdge_1040737038.qPKW.14.5" departSpeed="max" departPos="last" departLane="best" route="1070403831#1-AddedOnRampEdge_1040737038.qPKW.14.5" number="4" begin="870.0" end="900.0"/>
    <flow id="1070403831#1-AddedOnRampEdge_19442635.qPKW.14.5" departSpeed="max" departPos="last" departLane="best" route="1070403831#1-AddedOnRampEdge_19442635.qPKW.14.5" number="10" begin="870.0" end="900.0"/>
    <flow id="19441652#0_19442635.qPKW.14.5" departSpeed="max" departPos="last" departLane="best" route="19441652#0_19442635.qPKW.14.5" number="34" begin="870.0" end="900.0"/>
    <flow id="277208926_634155175.qPKW.14.5" departSpeed="max" departPos="last" departLane="best" route="277208926_634155175.qPKW.14.5" number="16" begin="870.0" end="900.0"/>
    <flow id="27828382_634155175.qPKW.14.5" departSpeed="max" departPos="last" departLane="best" route="27828382_634155175.qPKW.14.5" number="17" begin="870.0" end="900.0"/>
    <flow id="1070403831#1-AddedOnRampEdge_1040737038.qPKW.15.0" departSpeed="max" departPos="last" departLane="best" route="1070403831#1-AddedOnRampEdge_1040737038.qPKW.15.0" number="10" begin="900.0" end="930.0"/>
    <flow id="1070403831#1-AddedOnRampEdge_19442635.qPKW.15.0" departSpeed="max" departPos="last" departLane="best" route="1070403831#1-AddedOnRampEdge_19442635.qPKW.15.0" number="4" begin="900.0" end="930.0"/>
    <flow id="19441652#0_19442635.qPKW.15.0" departSpeed="max" departPos="last" departLane="best" route="19441652#0_19442635.qPKW.15.0" number="13" begin="900.0" end="930.0"/>
    <flow id="277208926_634155175.qPKW.15.0" departSpeed="max" departPos="last" departLane="best" route="277208926_634155175.qPKW.15.0" number="49" begin="900.0" end="930.0"/>
    <flow id="27828382_634155175.qPKW.15.0" departSpeed="max" departPos="last" departLane="best" route="27828382_634155175.qPKW.15.0" number="17" begin="900.0" end="930.0"/>
    <flow id="1070403831#1-AddedOnRampEdge_19442635.qPKW.15.5" departSpeed="max" departPos="last" departLane="best" route="1070403831#1-AddedOnRampEdge_19442635.qPKW.15.5" number="18" begin="930.0" end="960.0"/>
    <flow id="19441652#0_19442635.qPKW.15.5" departSpeed="max" departPos="last" departLane="best" route="19441652#0_19442635.qPKW.15.5" number="7" begin="930.0" end="960.0"/>
    <flow id="277208926_634155175.qPKW.15.5" departSpeed="max" departPos="last" departLane="best" route="277208926_634155175.qPKW.15.5" number="27" begin="930.0" end="960.0"/>
    <flow id="27828382_634155175.qPKW.15.5" departSpeed="max" departPos="last" departLane="best" route="27828382_634155175.qPKW.15.5" number="16" begin="930.0" end="960.0"/>
    <flow id="1070403831#1-AddedOnRampEdge_1040737038.qPKW.16.0" departSpeed="max" departPos="last" departLane="best" route="1070403831#1-AddedOnRampEdge_1040737038.qPKW.16.0" number="4" begin="960.0" end="990.0"/>
    <flow id="19441652#0_19442635.qPKW.16.0" departSpeed="max" departPos="last" departLane="best" route="19441652#0_19442635.qPKW.16.0" number="22" begin="960.0" end="990.0"/>
    <flow id="277208926_634155175.qPKW.16.0" departSpeed="max" departPos="last" departLane="best" route="277208926_634155175.qPKW.16.0" number="19" begin="960.0" end="990.0"/>
    <flow id="27828382_1040737038.qPKW.16.0" departSpeed="max" departPos="last" departLane="best" route="27828382_1040737038.qPKW.16.0" number="6" begin="960.0" end="990.0"/>
    <flow id="27828382_634155175.qPKW.16.0" departSpeed="max" departPos="last" departLane="best" route="27828382_634155175.qPKW.16.0" number="11" begin="960.0" end="990.0"/>
    <flow id="19441652#0_19442635.qPKW.16.5" departSpeed="max" departPos="last" departLane="best" route="19441652#0_19442635.qPKW.16.5" number="10" begin="990.0" end="1020.0"/>
    <flow id="277208926_634155175.qPKW.16.5" departSpeed="max" departPos="last" departLane="best" route="277208926_634155175.qPKW.16.5" number="19" begin="990.0" end="1020.0"/>
    <flow id="27828382_634155175.qPKW.16.5" departSpeed="max" departPos="last" departLane="best" route="27828382_634155175.qPKW.16.5" number="12" begin="990.0" end="1020.0"/>
    <flow id="19441652#0_19442635.qPKW.17.0" departSpeed="max" departPos="last" departLane="best" route="19441652#0_19442635.qPKW.17.0" number="10" begin="1020.0" end="1050.0"/>
    <flow id="277208926_634155175.qPKW.17.0" departSpeed="max" departPos="last" departLane="best" route="277208926_634155175.qPKW.17.0" number="13" begin="1020.0" end="1050.0"/>
    <flow id="27828382_1040737038.qPKW.17.0" departSpeed="max" departPos="last" departLane="best" route="27828382_1040737038.qPKW.17.0" number="6" begin="1020.0" end="1050.0"/>
    <flow id="27828382_634155175.qPKW.17.0" departSpeed="max" departPos="last" departLane="best" route="27828382_634155175.qPKW.17.0" number="9" begin="1020.0" end="1050.0"/>
    <flow id="19441652#0_19442635.qPKW.17.5" departSpeed="max" departPos="last" departLane="best" route="19441652#0_19442635.qPKW.17.5" number="3" begin="1050.0" end="1080.0"/>
    <flow id="277208926_634155175.qPKW.17.5" departSpeed="max" departPos="last" departLane="best" route="277208926_634155175.qPKW.17.5" number="6" begin="1050.0" end="1080.0"/>
    <flow id="27828382_634155175.qPKW.17.5" departSpeed="max" departPos="last" departLane="best" route="27828382_634155175.qPKW.17.5" number="12" begin="1050.0" end="1080.0"/>
    <flow id="19441652#0_19442635.qPKW.18.0" departSpeed="max" departPos="last" departLane="best" route="19441652#0_19442635.qPKW.18.0" number="5" begin="1080.0" end="1110.0"/>
    <flow id="277208926_634155175.qPKW.18.0" departSpeed="max" departPos="last" departLane="best" route="277208926_634155175.qPKW.18.0" number="3" begin="1080.0" end="1110.0"/>
    <flow id="27828382_1040737038.qPKW.18.0" departSpeed="max" departPos="last" departLane="best" route="27828382_1040737038.qPKW.18.0" number="4" begin="1080.0" end="1110.0"/>
    <flow id="27828382_634155175.qPKW.18.0" departSpeed="max" departPos="last" departLane="best" route="27828382_634155175.qPKW.18.0" number="12" begin="1080.0" end="1110.0"/>
    <flow id="19441652#0_19442635.qPKW.18.5" departSpeed="max" departPos="last" departLane="best" route="19441652#0_19442635.qPKW.18.5" number="6" begin="1110.0" end="1140.0"/>
    <flow id="277208926_634155175.qPKW.18.5" departSpeed="max" departPos="last" departLane="best" route="277208926_634155175.qPKW.18.5" number="3" begin="1110.0" end="1140.0"/>
    <flow id="27828382_634155175.qPKW.18.5" departSpeed="max" departPos="last" departLane="best" route="27828382_634155175.qPKW.18.5" number="13" begin="1110.0" end="1140.0"/>
    <flow id="19441652#0_19442635.qPKW.19.0" departSpeed="max" departPos="last" departLane="best" route="19441652#0_19442635.qPKW.19.0" number="7" begin="1140.0" end="1170.0"/>
    <flow id="277208926_634155175.qPKW.19.0" departSpeed="max" departPos="last" departLane="best" route="277208926_634155175.qPKW.19.0" number="6" begin="1140.0" end="1170.0"/>
    <flow id="27828382_1040737038.qPKW.19.0" departSpeed="max" departPos="last" departLane="best" route="27828382_1040737038.qPKW.19.0" number="1" begin="1140.0" end="1170.0"/>
    <flow id="27828382_634155175.qPKW.19.0" departSpeed="max" departPos="last" departLane="best" route="27828382_634155175.qPKW.19.0" number="12" begin="1140.0" end="1170.0"/>
    <flow id="1070403831#1-AddedOnRampEdge_1040737038.qPKW.19.5" departSpeed="max" departPos="last" departLane="best" route="1070403831#1-AddedOnRampEdge_1040737038.qPKW.19.5" number="5" begin="1170.0" end="1200.0"/>
    <flow id="1070403831#1-AddedOnRampEdge_19442635.qPKW.19.5" departSpeed="max" departPos="last" departLane="best" route="1070403831#1-AddedOnRampEdge_19442635.qPKW.19.5" number="3" begin="1170.0" end="1200.0"/>
    <flow id="277208926_634155175.qPKW.19.5" departSpeed="max" departPos="last" departLane="best" route="277208926_634155175.qPKW.19.5" number="1" begin="1170.0" end="1200.0"/>
    <flow id="27828382_634155175.qPKW.19.5" departSpeed="max" departPos="last" departLane="best" route="27828382_634155175.qPKW.19.5" number="17" begin="1170.0" end="1200.0"/>
    <flow id="1070403831#1-AddedOnRampEdge_19442635.qPKW.20.0" departSpeed="max" departPos="last" departLane="best" route="1070403831#1-AddedOnRampEdge_19442635.qPKW.20.0" number="13" begin="1200.0" end="1230.0"/>
    <flow id="19441652#0_19442635.qPKW.20.0" departSpeed="max" departPos="last" departLane="best" route="19441652#0_19442635.qPKW.20.0" number="1" begin="1200.0" end="1230.0"/>
    <flow id="277208926_634155175.qPKW.20.0" departSpeed="max" departPos="last" departLane="best" route="277208926_634155175.qPKW.20.0" number="1" begin="1200.0" end="1230.0"/>
    <flow id="27828382_634155175.qPKW.20.0" departSpeed="max" departPos="last" departLane="best" route="27828382_634155175.qPKW.20.0" number="15" begin="1200.0" end="1230.0"/>
    <flow id="1070403831#1-AddedOnRampEdge_1040737038.qPKW.20.5" departSpeed="max" departPos="last" departLane="best" route="1070403831#1-AddedOnRampEdge_1040737038.qPKW.20.5" number="9" begin="1230.0" end="1260.0"/>
    <flow id="1070403831#1-AddedOnRampEdge_19442635.qPKW.20.5" departSpeed="max" departPos="last" departLane="best" route="1070403831#1-AddedOnRampEdge_19442635.qPKW.20.5" number="7" begin="1230.0" end="1260.0"/>
    <flow id="19441652#0_19442635.qPKW.20.5" departSpeed="max" departPos="last" departLane="best" route="19441652#0_19442635.qPKW.20.5" number="15" begin="1230.0" end="1260.0"/>
    <flow id="277208926_634155175.qPKW.20.5" departSpeed="max" departPos="last" departLane="best" route="277208926_634155175.qPKW.20.5" number="1" begin="1230.0" end="1260.0"/>
    <flow id="27828382_634155175.qPKW.20.5" departSpeed="max" departPos="last" departLane="best" route="27828382_634155175.qPKW.20.5" number="18" begin="1230.0" end="1260.0"/>
    <flow id="1070403831#1-AddedOnRampEdge_1040737038.qPKW.21.0" departSpeed="max" departPos="last" departLane="best" route="1070403831#1-AddedOnRampEdge_1040737038.qPKW.21.0" number="11" begin="1260.0" end="1290.0"/>
    <flow id="1070403831#1-AddedOnRampEdge_19442635.qPKW.21.0" departSpeed="max" departPos="last" departLane="best" route="1070403831#1-AddedOnRampEdge_19442635.qPKW.21.0" number="8" begin="1260.0" end="1290.0"/>
    <flow id="19441652#0_19442635.qPKW.21.0" departSpeed="max" departPos="last" departLane="best" route="19441652#0_19442635.qPKW.21.0" number="1" begin="1260.0" end="1290.0"/>
    <flow id="277208926_634155175.qPKW.21.0" departSpeed="max" departPos="last" departLane="best" route="277208926_634155175.qPKW.21.0" number="2" begin="1260.0" end="1290.0"/>
    <flow id="27828382_634155175.qPKW.21.0" departSpeed="max" departPos="last" departLane="best" route="27828382_634155175.qPKW.21.0" number="16" begin="1260.0" end="1290.0"/>
    <flow id="1070403831#1-AddedOnRampEdge_1040737038.qPKW.21.5" departSpeed="max" departPos="last" departLane="best" route="1070403831#1-AddedOnRampEdge_1040737038.qPKW.21.5" number="1" begin="1290.0" end="1320.0"/>
    <flow id="1070403831#1-AddedOnRampEdge_19442635.qPKW.21.5" departSpeed="max" departPos="last" departLane="best" route="1070403831#1-AddedOnRampEdge_19442635.qPKW.21.5" number="15" begin="1290.0" end="1320.0"/>
    <flow id="19441652#0_19442635.qPKW.21.5" departSpeed="max" departPos="last" departLane="best" route="19441652#0_19442635.qPKW.21.5" number="1" begin="1290.0" end="1320.0"/>
    <flow id="277208926_634155175.qPKW.21.5" departSpeed="max" departPos="last" departLane="best" route="277208926_634155175.qPKW.21.5" number="23" begin="1290.0" end="1320.0"/>
    <flow id="27828382_634155175.qPKW.21.5" departSpeed="max" departPos="last" departLane="best" route="27828382_634155175.qPKW.21.5" number="17" begin="1290.0" end="1320.0"/>
    <flow id="1070403831#1-AddedOnRampEdge_1040737038.qPKW.22.0" departSpeed="max" departPos="last" departLane="best" route="1070403831#1-AddedOnRampEdge_1040737038.qPKW.22.0" number="9" begin="1320.0" end="1350.0"/>
    <flow id="1070403831#1-AddedOnRampEdge_19442635.qPKW.22.0" departSpeed="max" departPos="last" departLane="best" route="1070403831#1-AddedOnRampEdge_19442635.qPKW.22.0" number="4" begin="1320.0" end="1350.0"/>
    <flow id="19441652#0_19442635.qPKW.22.0" departSpeed="max" departPos="last" departLane="best" route="19441652#0_19442635.qPKW.22.0" number="17" begin="1320.0" end="1350.0"/>
    <flow id="277208926_634155175.qPKW.22.0" departSpeed="max" departPos="last" departLane="best" route="277208926_634155175.qPKW.22.0" number="18" begin="1320.0" end="1350.0"/>
    <flow id="27828382_634155175.qPKW.22.0" departSpeed="max" departPos="last" departLane="best" route="27828382_634155175.qPKW.22.0" number="14" begin="1320.0" end="1350.0"/>
    <flow id="1070403831#1-AddedOnRampEdge_1040737038.qPKW.22.5" departSpeed="max" departPos="last" departLane="best" route="1070403831#1-AddedOnRampEdge_1040737038.qPKW.22.5" number="4" begin="1350.0" end="1380.0"/>
    <flow id="19441652#0_19442635.qPKW.22.5" departSpeed="max" departPos="last" departLane="best" route="19441652#0_19442635.qPKW.22.5" number="7" begin="1350.0" end="1380.0"/>
    <flow id="277208926_634155175.qPKW.22.5" departSpeed="max" departPos="last" departLane="best" route="277208926_634155175.qPKW.22.5" number="20" begin="1350.0" end="1380.0"/>
    <flow id="27828382_1040737038.qPKW.22.5" departSpeed="max" departPos="last" departLane="best" route="27828382_1040737038.qPKW.22.5" number="4" begin="1350.0" end="1380.0"/>
    <flow id="27828382_634155175.qPKW.22.5" departSpeed="max" departPos="last" departLane="best" route="27828382_634155175.qPKW.22.5" number="14" begin="1350.0" end="1380.0"/>
    <flow id="1070403831#1-AddedOnRampEdge_1040737038.qPKW.23.0" departSpeed="max" departPos="last" departLane="best" route="1070403831#1-AddedOnRampEdge_1040737038.qPKW.23.0" number="5" begin="1380.0" end="1410.0"/>
    <flow id="1070403831#1-AddedOnRampEdge_19442635.qPKW.23.0" departSpeed="max" departPos="last" departLane="best" route="1070403831#1-AddedOnRampEdge_19442635.qPKW.23.0" number="3" begin="1380.0" end="1410.0"/>
    <flow id="277208926_634155175.qPKW.23.0" departSpeed="max" departPos="last" departLane="best" route="277208926_634155175.qPKW.23.0" number="3" begin="1380.0" end="1410.0"/>
    <flow id="27828382_634155175.qPKW.23.0" departSpeed="max" departPos="last" departLane="best" route="27828382_634155175.qPKW.23.0" number="17" begin="1380.0" end="1410.0"/>
    <flow id="1070403831#1-AddedOnRampEdge_1040737038.qPKW.23.5" departSpeed="max" departPos="last" departLane="best" route="1070403831#1-AddedOnRampEdge_1040737038.qPKW.23.5" number="5" begin="1410.0" end="1440.0"/>
    <flow id="19441652#0_19442635.qPKW.23.5" departSpeed="max" departPos="last" departLane="best" route="19441652#0_19442635.qPKW.23.5" number="7" begin="1410.0" end="1440.0"/>
    <flow id="277208926_634155175.qPKW.23.5" departSpeed="max" departPos="last" departLane="best" route="277208926_634155175.qPKW.23.5" number="2" begin="1410.0" end="1440.0"/>
    <flow id="27828382_1040737038.qPKW.23.5" departSpeed="max" departPos="last" departLane="best" route="27828382_1040737038.qPKW.23.5" number="1" begin="1410.0" end="1440.0"/>
    <flow id="27828382_634155175.qPKW.23.5" departSpeed="max" departPos="last" departLane="best" route="27828382_634155175.qPKW.23.5" number="15" begin="1410.0" end="1440.0"/>
    <flow id="19441652#0_19442635.qPKW.24.0" departSpeed="max" departPos="last" departLane="best" route="19441652#0_19442635.qPKW.24.0" number="9" begin="1440.0" end="1470.0"/>
    <flow id="277208926_634155175.qPKW.24.0" departSpeed="max" departPos="last" departLane="best" route="277208926_634155175.qPKW.24.0" number="9" begin="1440.0" end="1470.0"/>
    <flow id="27828382_1040737038.qPKW.24.0" departSpeed="max" departPos="last" departLane="best" route="27828382_1040737038.qPKW.24.0" number="5" begin="1440.0" end="1470.0"/>
    <flow id="27828382_634155175.qPKW.24.0" departSpeed="max" departPos="last" departLane="best" route="27828382_634155175.qPKW.24.0" number="10" begin="1440.0" end="1470.0"/>
    <flow id="19441652#0_19442635.qPKW.24.5" departSpeed="max" departPos="last" departLane="best" route="19441652#0_19442635.qPKW.24.5" number="4" begin="1470.0" end="1500.0"/>
    <flow id="277208926_634155175.qPKW.24.5" departSpeed="max" departPos="last" departLane="best" route="277208926_634155175.qPKW.24.5" number="7" begin="1470.0" end="1500.0"/>
    <flow id="27828382_1040737038.qPKW.24.5" departSpeed="max" departPos="last" departLane="best" route="27828382_1040737038.qPKW.24.5" number="1" begin="1470.0" end="1500.0"/>
    <flow id="27828382_634155175.qPKW.24.5" departSpeed="max" departPos="last" departLane="best" route="27828382_634155175.qPKW.24.5" number="12" begin="1470.0" end="1500.0"/>
    <flow id="19441652#0_19442635.qPKW.25.0" departSpeed="max" departPos="last" departLane="best" route="19441652#0_19442635.qPKW.25.0" number="6" begin="1500.0" end="1530.0"/>
    <flow id="277208926_634155175.qPKW.25.0" departSpeed="max" departPos="last" departLane="best" route="277208926_634155175.qPKW.25.0" number="5" begin="1500.0" end="1530.0"/>
    <flow id="27828382_634155175.qPKW.25.0" departSpeed="max" departPos="last" departLane="best" route="27828382_634155175.qPKW.25.0" number="10" begin="1500.0" end="1530.0"/>
    <flow id="1070403831#1-AddedOnRampEdge_1040737038.qPKW.25.5" departSpeed="max" departPos="last" departLane="best" route="1070403831#1-AddedOnRampEdge_1040737038.qPKW.25.5" number="14" begin="1530.0" end="1560.0"/>
    <flow id="19441652#0_19442635.qPKW.25.5" departSpeed="max" departPos="last" departLane="best" route="19441652#0_19442635.qPKW.25.5" number="5" begin="1530.0" end="1560.0"/>
    <flow id="277208926_634155175.qPKW.25.5" departSpeed="max" departPos="last" departLane="best" route="277208926_634155175.qPKW.25.5" number="6" begin="1530.0" end="1560.0"/>
    <flow id="27828382_1040737038.qPKW.25.5" departSpeed="max" departPos="last" departLane="best" route="27828382_1040737038.qPKW.25.5" number="8" begin="1530.0" end="1560.0"/>
    <flow id="27828382_634155175.qPKW.25.5" departSpeed="max" departPos="last" departLane="best" route="27828382_634155175.qPKW.25.5" number="8" begin="1530.0" end="1560.0"/>
    <flow id="1070403831#1-AddedOnRampEdge_19440902.qPKW.26.0" departSpeed="max" departPos="last" departLane="best" route="1070403831#1-AddedOnRampEdge_19440902.qPKW.26.0" number="4" begin="1560.0" end="1590.0"/>
    <flow id="27828382_1040737038.qPKW.26.0" departSpeed="max" departPos="last" departLane="best" route="27828382_1040737038.qPKW.26.0" number="2" begin="1560.0" end="1590.0"/>
    <flow id="27828382_634155175.qPKW.26.0" departSpeed="max" departPos="last" departLane="best" route="27828382_634155175.qPKW.26.0" number="16" begin="1560.0" end="1590.0"/>
    <flow id="1070403831#1-AddedOnRampEdge_1040737038.qPKW.26.5" departSpeed="max" departPos="last" departLane="best" route="1070403831#1-AddedOnRampEdge_1040737038.qPKW.26.5" number="14" begin="1590.0" end="1620.0"/>
    <flow id="19441652#0_19442635.qPKW.26.5" departSpeed="max" departPos="last" departLane="best" route="19441652#0_19442635.qPKW.26.5" number="7" begin="1590.0" end="1620.0"/>
    <flow id="27828382_1040737038.qPKW.26.5" departSpeed="max" departPos="last" departLane="best" route="27828382_1040737038.qPKW.26.5" number="4" begin="1590.0" end="1620.0"/>
    <flow id="27828382_634155175.qPKW.26.5" departSpeed="max" departPos="last" departLane="best" route="27828382_634155175.qPKW.26.5" number="13" begin="1590.0" end="1620.0"/>
    <flow id="1070403831#1-AddedOnRampEdge_1040737038.qPKW.27.0" departSpeed="max" departPos="last" departLane="best" route="1070403831#1-AddedOnRampEdge_1040737038.qPKW.27.0" number="7" begin="1620.0" end="1650.0"/>
    <flow id="1070403831#1-AddedOnRampEdge_19442635.qPKW.27.0" departSpeed="max" departPos="last" departLane="best" route="1070403831#1-AddedOnRampEdge_19442635.qPKW.27.0" number="11" begin="1620.0" end="1650.0"/>
    <flow id="27828382_1040737038.qPKW.27.0" departSpeed="max" departPos="last" departLane="best" route="27828382_1040737038.qPKW.27.0" number="3" begin="1620.0" end="1650.0"/>
    <flow id="27828382_634155175.qPKW.27.0" departSpeed="max" departPos="last" departLane="best" route="27828382_634155175.qPKW.27.0" number="14" begin="1620.0" end="1650.0"/>
    <flow id="19441652#0_19442635.qPKW.27.5" departSpeed="max" departPos="last" departLane="best" route="19441652#0_19442635.qPKW.27.5" number="21" begin="1650.0" end="1680.0"/>
    <flow id="27828382_19442635.qPKW.27.5" departSpeed="max" departPos="last" departLane="best" route="27828382_19442635.qPKW.27.5" number="5" begin="1650.0" end="1680.0"/>
    <flow id="27828382_634155175.qPKW.27.5" departSpeed="max" departPos="last" departLane="best" route="27828382_634155175.qPKW.27.5" number="9" begin="1650.0" end="1680.0"/>
    <flow id="277208926_634155175.qPKW.28.0" departSpeed="max" departPos="last" departLane="best" route="277208926_634155175.qPKW.28.0" number="13" begin="1680.0" end="1710.0"/>
    <flow id="27828382_1040737038.qPKW.28.0" departSpeed="max" departPos="last" departLane="best" route="27828382_1040737038.qPKW.28.0" number="3" begin="1680.0" end="1710.0"/>
    <flow id="27828382_634155175.qPKW.28.0" departSpeed="max" departPos="last" departLane="best" route="27828382_634155175.qPKW.28.0" number="12" begin="1680.0" end="1710.0"/>
    <flow id="19441652#0_19442635.qPKW.28.5" departSpeed="max" departPos="last" departLane="best" route="19441652#0_19442635.qPKW.28.5" number="2" begin="1710.0" end="1740.0"/>
    <flow id="277208926_634155175.qPKW.28.5" departSpeed="max" departPos="last" departLane="best" route="277208926_634155175.qPKW.28.5" number="11" begin="1710.0" end="1740.0"/>
    <flow id="27828382_634155175.qPKW.28.5" departSpeed="max" departPos="last" departLane="best" route="27828382_634155175.qPKW.28.5" number="2" begin="1710.0" end="1740.0"/>
    <flow id="19441652#0_19442635.qPKW.29.0" departSpeed="max" departPos="last" departLane="best" route="19441652#0_19442635.qPKW.29.0" number="4" begin="1740.0" end="1770.0"/>
    <flow id="277208926_634155175.qPKW.29.0" departSpeed="max" departPos="last" departLane="best" route="277208926_634155175.qPKW.29.0" number="6" begin="1740.0" end="1770.0"/>
    <flow id="27828382_1040737038.qPKW.29.0" departSpeed="max" departPos="last" departLane="best" route="27828382_1040737038.qPKW.29.0" number="1" begin="1740.0" end="1770.0"/>
    <flow id="27828382_634155175.qPKW.29.0" departSpeed="max" departPos="last" departLane="best" route="27828382_634155175.qPKW.29.0" number="3" begin="1740.0" end="1770.0"/>
    <flow id="277208926_634155175.qPKW.29.5" departSpeed="max" departPos="last" departLane="best" route="277208926_634155175.qPKW.29.5" number="6" begin="1770.0" end="1800.0"/>
    <flow id="27828382_1040737038.qPKW.29.5" departSpeed="max" departPos="last" departLane="best" route="27828382_1040737038.qPKW.29.5" number="1" begin="1770.0" end="1800.0"/>
    <flow id="27828382_634155175.qPKW.29.5" departSpeed="max" departPos="last" departLane="best" route="27828382_634155175.qPKW.29.5" number="3" begin="1770.0" end="1800.0"/>
</additional>
